{"id":6722810,"resource_state":3,"name":"Cret au Merle","activity_type":"NordicSki","distance":1186.5,"average_grade":6.7,"maximum_grade":21.8,"elevation_high":1302.2,"elevation_low":1223.0,"start_latlng":[46.267951,5.86979],"end_latlng":[46.266446,5.877972],"start_latitude":46.267951,"start_longitude":5.86979,"end_latitude":46.266446,"end_longitude":5.877972,"climb_category":0,"city":"La Pesse","state":"Franche-Comté","country":"France","private":false,"hazardous":false,"starred":false,"created_at":"2014-02-22T13:06:42Z","updated_at":"2017-12-21T09:05:33Z","total_elevation_gain":81.6,"map":{"id":"s6722810","polyline":"uukyGemyb@j@|@RVJHj@TZDz@Vb@Fx@K^?PC`BFv@K~@]TQJMJ]OgAQa@SyAUyCe@kBAqAEWKQ[SWe@Qa@Io@Mc@WWK_@Bm@?aAKoAMw@KY_@i@Ce@N[TWC[GQYa@YYOS_@y@MOM]Ga@?uAGs@Fa@NIZCT?d@DXO","resource_state":3},"effort_count":133,"athlete_count":85,"star_count":0,"athlete_segment_stats":{"pr_elapsed_time":null,"pr_date":null,"effort_count":0}}