{"id":14369541,"resource_state":3,"name":"Rocher du Chateau (partie 2)","activity_type":"NordicSki","distance":3670.8,"average_grade":-0.2,"maximum_grade":27.0,"elevation_high":1736.6,"elevation_low":1718.6,"start_latlng":[45.337174,7.021612],"end_latlng":[45.331847,7.016246],"start_latitude":45.337174,"start_longitude":7.021612,"end_latitude":45.331847,"end_longitude":7.016246,"climb_category":0,"city":"Bessans","state":"Auvergne-Rhône-Alpes","country":"France","private":false,"hazardous":false,"starred":false,"created_at":"2017-03-17T08:00:05Z","updated_at":"2017-12-21T09:08:08Z","total_elevation_gain":17.6,"map":{"id":"s14369541","polyline":"i|usGalzi@_CqB_BiAgA_AOGw@g@_Ay@SUYQ]IUC[IMKg@QQM]CcDy@SOQ]OQYEWBe@Pg@@_@F}AWc@HM?GB[BU?EAUU_@UKCu@CYKMUGe@@YBQFKJETAJ@VHN?NANIh@g@d@YXGPUD[Cc@Qk@OmAIYOQKESGK@KEMBMAa@BQEU?{@H}@?YMGE}@cAYg@SMWCwAo@[Ie@EUKYAa@NKVANPb@VXv@t@LDTDp@DTHLNFV?PDRDn@r@bCn@~Ap@lDJ\\P^b@l@ZZXHf@Al@U^u@JINEf@?pAVj@XTBfAATFFBJNXbADJJJLFTB|@YH?v@LlBPHARIj@_@R?TJp@`@LPN\\Lv@L^b@t@dAvAZ\\JHT@j@_@PC`@JZNhBpB|ArBf@Zr@R\\TlBjBrAbBlAnA~@jBz@xBPXNHRFlCBbANPNRl@HPLDT@NF`AbAXt@JH","resource_state":3},"effort_count":595,"athlete_count":193,"star_count":0,"athlete_segment_stats":{"pr_elapsed_time":null,"pr_date":null,"effort_count":0}}