{"effort_count":182,"entry_count":182,"neighborhood_count":1,"kom_type":"kom","entries":[{"athlete_name":"Paco Zapato","athlete_id":16428362,"athlete_gender":"M","average_hr":null,"average_watts":null,"distance":2028.7,"elapsed_time":511,"moving_time":511,"start_date":"2017-02-25T08:06:35Z","start_date_local":"2017-02-25T09:06:35Z","activity_id":878734849,"effort_id":21389104229,"rank":1,"neighborhood_index":0,"athlete_profile":"https://dgalywyr863hv.cloudfront.net/pictures/athletes/16428362/4590008/1/large.jpg"},{"athlete_name":"Sylvain Mnz","athlete_id":17445389,"athlete_gender":"M","average_hr":null,"average_watts":null,"distance":1972.4,"elapsed_time":600,"moving_time":600,"start_date":"2017-02-14T11:34:18Z","start_date_local":"2017-02-14T12:34:18Z","activity_id":865995909,"effort_id":21087138237,"rank":2,"neighborhood_index":0,"athlete_profile":"avatar/athlete/large.png"},{"athlete_name":"Gilbert Rahmouni","athlete_id":3384437,"athlete_gender":"M","average_hr":100.0,"average_watts":null,"distance":2064.1,"elapsed_time":619,"moving_time":619,"start_date":"2010-01-16T13:09:08Z","start_date_local":"2010-01-16T13:09:08Z","activity_id":95327159,"effort_id":2781944826,"rank":3,"neighborhood_index":0,"athlete_profile":"https://dgalywyr863hv.cloudfront.net/pictures/athletes/3384437/1089987/1/large.jpg"},{"athlete_name":"Kévin Dayet","athlete_id":1743121,"athlete_gender":"M","average_hr":167.9,"average_watts":null,"distance":2044.0,"elapsed_time":623,"moving_time":623,"start_date":"2017-02-18T05:56:26Z","start_date_local":"2017-02-18T06:56:26Z","activity_id":870210177,"effort_id":21184047335,"rank":4,"neighborhood_index":0,"athlete_profile":"https://dgalywyr863hv.cloudfront.net/pictures/athletes/1743121/1502448/4/large.jpg"},{"athlete_name":"Julien Dehaudt","athlete_id":5988035,"athlete_gender":"M","average_hr":null,"average_watts":null,"distance":2063.0,"elapsed_time":637,"moving_time":637,"start_date":"2015-03-17T08:00:01Z","start_date_local":"2015-03-17T09:00:01Z","activity_id":269551419,"effort_id":12302517920,"rank":5,"neighborhood_index":0,"athlete_profile":"https://dgalywyr863hv.cloudfront.net/pictures/athletes/5988035/1828970/12/large.jpg"},{"athlete_name":"Marcel Flaux","athlete_id":3692497,"athlete_gender":"M","average_hr":null,"average_watts":null,"distance":2098.7,"elapsed_time":640,"moving_time":640,"start_date":"2017-02-25T09:11:11Z","start_date_local":"2017-02-25T10:11:11Z","activity_id":878898628,"effort_id":21393174779,"rank":6,"neighborhood_index":0,"athlete_profile":"https://dgalywyr863hv.cloudfront.net/pictures/athletes/3692497/2868561/1/large.jpg"},{"athlete_name":"thom jallif","athlete_id":7192094,"athlete_gender":"M","average_hr":null,"average_watts":null,"distance":2081.5,"elapsed_time":646,"moving_time":646,"start_date":"2017-02-23T08:01:30Z","start_date_local":"2017-02-23T09:01:30Z","activity_id":876641701,"effort_id":21341767557,"rank":7,"neighborhood_index":0,"athlete_profile":"https://dgalywyr863hv.cloudfront.net/pictures/athletes/7192094/3165097/13/large.jpg"},{"athlete_name":"Pat jalliff","athlete_id":2315027,"athlete_gender":"M","average_hr":null,"average_watts":null,"distance":1990.1,"elapsed_time":651,"moving_time":651,"start_date":"2017-02-19T06:53:22Z","start_date_local":"2017-02-19T07:53:22Z","activity_id":871593990,"effort_id":21221136554,"rank":8,"neighborhood_index":0,"athlete_profile":"https://dgalywyr863hv.cloudfront.net/pictures/athletes/2315027/1126101/5/large.jpg"},{"athlete_name":"Sylvain GAULIER","athlete_id":3904456,"athlete_gender":"M","average_hr":null,"average_watts":null,"distance":2024.8,"elapsed_time":654,"moving_time":654,"start_date":"2014-01-08T08:13:27Z","start_date_local":"2014-01-08T09:13:27Z","activity_id":112771698,"effort_id":2781945019,"rank":9,"neighborhood_index":0,"athlete_profile":"https://dgalywyr863hv.cloudfront.net/pictures/athletes/3904456/1257464/1/large.jpg"}]}