{"effort_count":126,"entry_count":126,"neighborhood_count":1,"kom_type":"kom","entries":[{"athlete_name":"vincent pialoux","athlete_id":3300956,"athlete_gender":null,"average_hr":165.0,"average_watts":null,"distance":5736.0,"elapsed_time":984,"moving_time":984,"start_date":"2014-03-14T08:48:28Z","start_date_local":"2014-03-14T09:48:28Z","activity_id":120507885,"effort_id":2682745494,"rank":1,"neighborhood_index":0,"athlete_profile":"https://dgalywyr863hv.cloudfront.net/pictures/athletes/3300956/1103518/1/large.jpg"},{"athlete_name":"Lorblanchet Thomas GLR","athlete_id":1975812,"athlete_gender":"M","average_hr":null,"average_watts":null,"distance":5702.2,"elapsed_time":1000,"moving_time":1000,"start_date":"2014-03-14T08:48:26Z","start_date_local":"2014-03-14T09:48:26Z","activity_id":120506853,"effort_id":2682732075,"rank":2,"neighborhood_index":0,"athlete_profile":"https://dgalywyr863hv.cloudfront.net/pictures/athletes/1975812/745342/4/large.jpg"},{"athlete_name":"Luc T","athlete_id":2768076,"athlete_gender":"M","average_hr":null,"average_watts":null,"distance":5783.4,"elapsed_time":1084,"moving_time":1084,"start_date":"2015-03-13T15:54:52Z","start_date_local":"2015-03-13T16:54:52Z","activity_id":267550954,"effort_id":6263094591,"rank":3,"neighborhood_index":0,"athlete_profile":"https://dgalywyr863hv.cloudfront.net/pictures/athletes/2768076/3361687/5/large.jpg"},{"athlete_name":"Stéphane Bonnevault","athlete_id":12538454,"athlete_gender":"M","average_hr":152.0,"average_watts":null,"distance":5777.1,"elapsed_time":1119,"moving_time":1119,"start_date":"2017-02-27T09:13:27Z","start_date_local":"2017-02-27T10:13:27Z","activity_id":881506905,"effort_id":21465483068,"rank":4,"neighborhood_index":0,"athlete_profile":"https://dgalywyr863hv.cloudfront.net/pictures/athletes/12538454/3741078/1/large.jpg"},{"athlete_name":"Geraud GDE","athlete_id":11883744,"athlete_gender":"M","average_hr":143.3,"average_watts":null,"distance":5774.8,"elapsed_time":1336,"moving_time":1336,"start_date":"2017-02-25T10:45:31Z","start_date_local":"2017-02-25T11:45:31Z","activity_id":878827781,"effort_id":21391141435,"rank":5,"neighborhood_index":0,"athlete_profile":"https://lh5.googleusercontent.com/-PtipKkoMJ4E/AAAAAAAAAAI/AAAAAAAAAAA/tyu-CUWhvjw/photo.jpg"},{"athlete_name":"Manu REYNAUD","athlete_id":3093932,"athlete_gender":"M","average_hr":null,"average_watts":null,"distance":5761.8,"elapsed_time":1349,"moving_time":1349,"start_date":"2013-03-10T09:42:02Z","start_date_local":"2013-03-10T10:42:02Z","activity_id":84872439,"effort_id":2273013089,"rank":6,"neighborhood_index":0,"athlete_profile":"https://dgalywyr863hv.cloudfront.net/pictures/athletes/3093932/992620/4/large.jpg"},{"athlete_name":"LAROCHE CAMILLE","athlete_id":438244,"athlete_gender":"M","average_hr":136.1,"average_watts":null,"distance":5713.0,"elapsed_time":1355,"moving_time":1355,"start_date":"2016-01-30T14:07:32Z","start_date_local":"2016-01-30T15:07:32Z","activity_id":484326514,"effort_id":11630560418,"rank":7,"neighborhood_index":0,"athlete_profile":"avatar/athlete/large.png"},{"athlete_name":"JM Ressegaire","athlete_id":7716518,"athlete_gender":"M","average_hr":155.3,"average_watts":null,"distance":5755.1,"elapsed_time":1364,"moving_time":1346,"start_date":"2016-03-18T09:28:07Z","start_date_local":"2016-03-18T10:28:07Z","activity_id":520394945,"effort_id":12507294847,"rank":8,"neighborhood_index":0,"athlete_profile":"https://graph.facebook.com/100000889505822/picture?height=256\u0026width=256"},{"athlete_name":"JC REYNAUD","athlete_id":2622479,"athlete_gender":"M","average_hr":null,"average_watts":null,"distance":5818.8,"elapsed_time":1368,"moving_time":1368,"start_date":"2013-03-10T09:41:45Z","start_date_local":"2013-03-10T10:41:45Z","activity_id":85235124,"effort_id":2273013009,"rank":9,"neighborhood_index":0,"athlete_profile":"https://dgalywyr863hv.cloudfront.net/pictures/athletes/2622479/4229955/2/large.jpg"}]}