{"effort_count":19,"entry_count":19,"neighborhood_count":1,"kom_type":"kom","entries":[{"athlete_name":"Vincent Vaudaux","athlete_id":2423764,"athlete_gender":"M","average_hr":null,"average_watts":null,"distance":550.2,"elapsed_time":150,"moving_time":150,"start_date":"2014-01-25T09:47:58Z","start_date_local":"2014-01-25T10:47:58Z","activity_id":108790521,"effort_id":2371139836,"rank":1,"neighborhood_index":0,"athlete_profile":"https://dgalywyr863hv.cloudfront.net/pictures/athletes/2423764/872108/5/large.jpg"},{"athlete_name":"Luc Saillet","athlete_id":3026186,"athlete_gender":"M","average_hr":null,"average_watts":null,"distance":630.0,"elapsed_time":159,"moving_time":159,"start_date":"2016-01-27T09:24:42Z","start_date_local":"2016-01-27T10:24:42Z","activity_id":479733672,"effort_id":11514275625,"rank":2,"neighborhood_index":0,"athlete_profile":"avatar/athlete/large.png"},{"athlete_name":"Philippe  Mesnier","athlete_id":2624543,"athlete_gender":"M","average_hr":null,"average_watts":null,"distance":758.7,"elapsed_time":170,"moving_time":170,"start_date":"2016-02-27T10:59:57Z","start_date_local":"2016-02-27T11:59:57Z","activity_id":503467886,"effort_id":12092170461,"rank":3,"neighborhood_index":0,"athlete_profile":"https://dgalywyr863hv.cloudfront.net/pictures/athletes/2624543/6128782/1/large.jpg"},{"athlete_name":"fabien tanguy","athlete_id":2167816,"athlete_gender":"M","average_hr":148.5,"average_watts":null,"distance":723.1,"elapsed_time":187,"moving_time":187,"start_date":"2016-02-22T09:47:01Z","start_date_local":"2016-02-22T10:47:01Z","activity_id":499500919,"effort_id":11993912151,"rank":4,"neighborhood_index":0,"athlete_profile":"https://dgalywyr863hv.cloudfront.net/pictures/athletes/2167816/4621268/3/large.jpg"},{"athlete_name":"Raphael Masliah","athlete_id":9396946,"athlete_gender":"M","average_hr":null,"average_watts":null,"distance":882.1,"elapsed_time":210,"moving_time":210,"start_date":"2016-02-22T09:00:08Z","start_date_local":"2016-02-22T10:00:08Z","activity_id":499515991,"effort_id":11994403189,"rank":5,"neighborhood_index":0,"athlete_profile":"https://dgalywyr863hv.cloudfront.net/pictures/athletes/9396946/2843527/2/large.jpg"},{"athlete_name":"Pierre EB","athlete_id":6444979,"athlete_gender":"M","average_hr":null,"average_watts":null,"distance":764.3,"elapsed_time":218,"moving_time":218,"start_date":"2016-02-18T09:21:20Z","start_date_local":"2016-02-18T10:21:20Z","activity_id":498462032,"effort_id":11969149008,"rank":6,"neighborhood_index":0,"athlete_profile":"https://dgalywyr863hv.cloudfront.net/pictures/athletes/6444979/3466649/2/large.jpg"},{"athlete_name":"Sophie B","athlete_id":12248233,"athlete_gender":"F","average_hr":null,"average_watts":null,"distance":739.0,"elapsed_time":222,"moving_time":222,"start_date":"2015-12-06T10:33:46Z","start_date_local":"2015-12-06T11:33:46Z","activity_id":445342545,"effort_id":10707386482,"rank":7,"neighborhood_index":0,"athlete_profile":"https://dgalywyr863hv.cloudfront.net/pictures/athletes/12248233/4258093/4/large.jpg"},{"athlete_name":"Billkoch manu","athlete_id":103516,"athlete_gender":"M","average_hr":null,"average_watts":null,"distance":833.1,"elapsed_time":237,"moving_time":237,"start_date":"2015-12-05T10:16:02Z","start_date_local":"2015-12-05T11:16:02Z","activity_id":444620230,"effort_id":10687787552,"rank":8,"neighborhood_index":0,"athlete_profile":"avatar/athlete/large.png"},{"athlete_name":"Gaëtan Tellier","athlete_id":6761707,"athlete_gender":"M","average_hr":160.3,"average_watts":null,"distance":916.5,"elapsed_time":249,"moving_time":249,"start_date":"2016-02-08T15:21:40Z","start_date_local":"2016-02-08T16:21:40Z","activity_id":492764394,"effort_id":11828227784,"rank":9,"neighborhood_index":0,"athlete_profile":"https://dgalywyr863hv.cloudfront.net/pictures/athletes/6761707/3589546/1/large.jpg"},{"athlete_name":"Michel CLEMENT","athlete_id":9179114,"athlete_gender":"M","average_hr":160.8,"average_watts":null,"distance":747.8,"elapsed_time":278,"moving_time":278,"start_date":"2016-01-26T10:01:52Z","start_date_local":"2016-01-26T11:01:52Z","activity_id":478847583,"effort_id":11495884644,"rank":10,"neighborhood_index":0,"athlete_profile":"https://dgalywyr863hv.cloudfront.net/pictures/athletes/9179114/5803598/1/large.jpg"}]}