{"effort_count":5,"entry_count":5,"neighborhood_count":1,"kom_type":"kom","entries":[{"athlete_name":"felix dejey","athlete_id":2861897,"athlete_gender":"M","average_hr":null,"average_watts":null,"distance":4256.2,"elapsed_time":1164,"moving_time":1164,"start_date":"2014-02-15T09:00:08Z","start_date_local":"2014-02-15T10:00:08Z","activity_id":113419760,"effort_id":2527019884,"rank":1,"neighborhood_index":0,"athlete_profile":"https://dgalywyr863hv.cloudfront.net/pictures/athletes/2861897/910361/1/large.jpg"},{"athlete_name":"Guillaume Fantin","athlete_id":1003085,"athlete_gender":"M","average_hr":null,"average_watts":null,"distance":4270.6,"elapsed_time":1452,"moving_time":1452,"start_date":"2014-02-16T09:07:27Z","start_date_local":"2014-02-16T10:07:27Z","activity_id":113696385,"effort_id":2507871137,"rank":2,"neighborhood_index":0,"athlete_profile":"https://dgalywyr863hv.cloudfront.net/pictures/athletes/1003085/891079/1/large.jpg"},{"athlete_name":"Sylvain Dhonneur","athlete_id":2990004,"athlete_gender":"M","average_hr":null,"average_watts":null,"distance":4298.7,"elapsed_time":1950,"moving_time":1950,"start_date":"2014-02-16T10:27:48Z","start_date_local":"2014-02-16T11:27:48Z","activity_id":113641443,"effort_id":2507842000,"rank":3,"neighborhood_index":0,"athlete_profile":"https://dgalywyr863hv.cloudfront.net/pictures/athletes/2990004/1096165/2/large.jpg"},{"athlete_name":"Jérôme Teisson","athlete_id":1112081,"athlete_gender":"M","average_hr":146.6,"average_watts":null,"distance":4292.0,"elapsed_time":2215,"moving_time":2185,"start_date":"2014-02-15T10:36:30Z","start_date_local":"2014-02-15T11:36:30Z","activity_id":113849944,"effort_id":2507871218,"rank":4,"neighborhood_index":0,"athlete_profile":"https://dgalywyr863hv.cloudfront.net/pictures/athletes/1112081/2302483/2/large.jpg"},{"athlete_name":"Ed Baker","athlete_id":258617,"athlete_gender":"M","average_hr":null,"average_watts":null,"distance":4174.7,"elapsed_time":2355,"moving_time":2061,"start_date":"2014-02-15T09:27:14Z","start_date_local":"2014-02-15T10:27:14Z","activity_id":113452208,"effort_id":2507871094,"rank":5,"neighborhood_index":0,"athlete_profile":"https://dgalywyr863hv.cloudfront.net/pictures/athletes/258617/51390/5/large.jpg"}]}