{"effort_count":157,"entry_count":157,"neighborhood_count":1,"kom_type":"kom","entries":[{"athlete_name":"Daniel CAMALET","athlete_id":9500924,"athlete_gender":"M","average_hr":138.4,"average_watts":null,"distance":2630.2,"elapsed_time":357,"moving_time":357,"start_date":"2017-03-11T09:33:36Z","start_date_local":"2017-03-11T10:33:36Z","activity_id":895602455,"effort_id":21813271392,"rank":1,"neighborhood_index":0,"athlete_profile":"https://dgalywyr863hv.cloudfront.net/pictures/athletes/9500924/4893778/2/large.jpg"},{"athlete_name":"vincent pialoux","athlete_id":3300956,"athlete_gender":null,"average_hr":null,"average_watts":null,"distance":2630.8,"elapsed_time":368,"moving_time":368,"start_date":"2017-02-27T09:11:40Z","start_date_local":"2017-02-27T10:11:40Z","activity_id":881455559,"effort_id":21617646148,"rank":2,"neighborhood_index":0,"athlete_profile":"https://dgalywyr863hv.cloudfront.net/pictures/athletes/3300956/1103518/1/large.jpg"},{"athlete_name":"Lorblanchet Thomas GLR","athlete_id":1975812,"athlete_gender":"M","average_hr":null,"average_watts":null,"distance":2635.7,"elapsed_time":369,"moving_time":369,"start_date":"2017-03-03T09:36:54Z","start_date_local":"2017-03-03T10:36:54Z","activity_id":885899649,"effort_id":21617646043,"rank":3,"neighborhood_index":0,"athlete_profile":"https://dgalywyr863hv.cloudfront.net/pictures/athletes/1975812/745342/4/large.jpg"},{"athlete_name":"Alexandre BIHL","athlete_id":5771678,"athlete_gender":"M","average_hr":null,"average_watts":null,"distance":2720.8,"elapsed_time":394,"moving_time":394,"start_date":"2015-03-15T11:11:31Z","start_date_local":"2015-03-15T12:11:31Z","activity_id":268445807,"effort_id":21617647958,"rank":4,"neighborhood_index":0,"athlete_profile":"https://dgalywyr863hv.cloudfront.net/pictures/athletes/5771678/3195373/3/large.jpg"},{"athlete_name":"Elise Chabbey","athlete_id":17418861,"athlete_gender":"F","average_hr":149.8,"average_watts":null,"distance":2643.4,"elapsed_time":395,"moving_time":395,"start_date":"2017-02-26T10:07:39Z","start_date_local":"2017-02-26T11:07:39Z","activity_id":880757932,"effort_id":21617646412,"rank":5,"neighborhood_index":0,"athlete_profile":"https://graph.facebook.com/10209988015158553/picture?height=256\u0026width=256"},{"athlete_name":"Luc T","athlete_id":2768076,"athlete_gender":"M","average_hr":null,"average_watts":null,"distance":2706.9,"elapsed_time":404,"moving_time":404,"start_date":"2016-03-20T09:04:18Z","start_date_local":"2016-03-20T10:04:18Z","activity_id":522307725,"effort_id":21617647305,"rank":6,"neighborhood_index":0,"athlete_profile":"https://dgalywyr863hv.cloudfront.net/pictures/athletes/2768076/3361687/5/large.jpg"},{"athlete_name":"Trail Fuchs","athlete_id":5733647,"athlete_gender":"M","average_hr":null,"average_watts":null,"distance":2722.4,"elapsed_time":409,"moving_time":409,"start_date":"2015-01-02T10:11:21Z","start_date_local":"2015-01-02T11:11:21Z","activity_id":238015138,"effort_id":21617648002,"rank":7,"neighborhood_index":0,"athlete_profile":"https://dgalywyr863hv.cloudfront.net/pictures/athletes/5733647/2352521/1/large.jpg"},{"athlete_name":"Adriano Dolci","athlete_id":10175515,"athlete_gender":"M","average_hr":null,"average_watts":null,"distance":2670.5,"elapsed_time":411,"moving_time":411,"start_date":"2017-02-18T10:06:36Z","start_date_local":"2017-02-18T11:06:36Z","activity_id":872767622,"effort_id":21617646748,"rank":8,"neighborhood_index":0,"athlete_profile":"https://dgalywyr863hv.cloudfront.net/pictures/athletes/10175515/3654287/4/large.jpg"},{"athlete_name":"Pierre Coutouly","athlete_id":6652393,"athlete_gender":"M","average_hr":null,"average_watts":null,"distance":2646.3,"elapsed_time":412,"moving_time":412,"start_date":"2017-02-19T10:54:07Z","start_date_local":"2017-02-19T11:54:07Z","activity_id":872143077,"effort_id":21617646541,"rank":9,"neighborhood_index":0,"athlete_profile":"https://dgalywyr863hv.cloudfront.net/pictures/athletes/6652393/2931478/1/large.jpg"}]}