{"effort_count":93,"entry_count":93,"neighborhood_count":1,"kom_type":"kom","entries":[{"athlete_name":"jean françois court","athlete_id":4717654,"athlete_gender":"M","average_hr":null,"average_watts":null,"distance":748.4,"elapsed_time":191,"moving_time":191,"start_date":"2016-01-24T08:58:00Z","start_date_local":"2016-01-24T09:58:00Z","activity_id":477570471,"effort_id":11459035302,"rank":1,"neighborhood_index":0,"athlete_profile":"https://dgalywyr863hv.cloudfront.net/pictures/athletes/4717654/1586892/4/large.jpg"},{"athlete_name":"Jézabel Kremer","athlete_id":2624110,"athlete_gender":"F","average_hr":null,"average_watts":null,"distance":740.2,"elapsed_time":205,"moving_time":205,"start_date":"2016-03-19T07:33:54Z","start_date_local":"2016-03-19T08:33:54Z","activity_id":520730364,"effort_id":12516057310,"rank":2,"neighborhood_index":0,"athlete_profile":"https://dgalywyr863hv.cloudfront.net/pictures/athletes/2624110/6175043/3/large.jpg"},{"athlete_name":"Guillaume Bellet","athlete_id":19469360,"athlete_gender":"M","average_hr":120.5,"average_watts":null,"distance":742.3,"elapsed_time":208,"moving_time":208,"start_date":"2017-01-30T08:55:04Z","start_date_local":"2017-01-30T09:55:04Z","activity_id":850140012,"effort_id":20723374750,"rank":3,"neighborhood_index":0,"athlete_profile":"https://dgalywyr863hv.cloudfront.net/pictures/athletes/19469360/7766520/1/large.jpg"},{"athlete_name":"Marco Penazzi","athlete_id":6903485,"athlete_gender":"M","average_hr":null,"average_watts":null,"distance":746.7,"elapsed_time":210,"moving_time":210,"start_date":"2016-03-12T08:48:30Z","start_date_local":"2016-03-12T09:48:30Z","activity_id":514809861,"effort_id":12368886185,"rank":4,"neighborhood_index":0,"athlete_profile":"https://dgalywyr863hv.cloudfront.net/pictures/athletes/6903485/2406789/1/large.jpg"},{"athlete_name":"Grégory Thouverey","athlete_id":7422393,"athlete_gender":null,"average_hr":null,"average_watts":null,"distance":747.4,"elapsed_time":219,"moving_time":219,"start_date":"2016-01-25T15:39:51Z","start_date_local":"2016-01-25T16:39:51Z","activity_id":478210687,"effort_id":11480183518,"rank":5,"neighborhood_index":0,"athlete_profile":"https://graph.facebook.com/10205703175358080/picture?height=256\u0026width=256"},{"athlete_name":"patrick vankerberghem","athlete_id":189303,"athlete_gender":"M","average_hr":78.5,"average_watts":null,"distance":731.8,"elapsed_time":232,"moving_time":232,"start_date":"2017-02-11T11:25:59Z","start_date_local":"2017-02-11T12:25:59Z","activity_id":862530702,"effort_id":21006570331,"rank":6,"neighborhood_index":0,"athlete_profile":"https://dgalywyr863hv.cloudfront.net/pictures/athletes/189303/36757/7/large.jpg"},{"athlete_name":"Perrin Rémi","athlete_id":9736340,"athlete_gender":"M","average_hr":null,"average_watts":null,"distance":715.0,"elapsed_time":235,"moving_time":235,"start_date":"2016-03-19T10:54:08Z","start_date_local":"2016-03-19T11:54:08Z","activity_id":522465563,"effort_id":12563558719,"rank":7,"neighborhood_index":0,"athlete_profile":"https://dgalywyr863hv.cloudfront.net/pictures/athletes/9736340/5782212/1/large.jpg"},{"athlete_name":"Luc Saillet","athlete_id":3026186,"athlete_gender":"M","average_hr":null,"average_watts":null,"distance":752.6,"elapsed_time":236,"moving_time":236,"start_date":"2015-03-07T04:38:20Z","start_date_local":"2015-03-07T05:38:20Z","activity_id":264497871,"effort_id":11159283878,"rank":8,"neighborhood_index":0,"athlete_profile":"avatar/athlete/large.png"},{"athlete_name":"Thomas Sogno","athlete_id":4556590,"athlete_gender":"M","average_hr":null,"average_watts":null,"distance":762.6,"elapsed_time":240,"moving_time":240,"start_date":"2016-03-12T08:49:05Z","start_date_local":"2016-03-12T09:49:05Z","activity_id":514887490,"effort_id":12371696543,"rank":9,"neighborhood_index":0,"athlete_profile":"https://dgalywyr863hv.cloudfront.net/pictures/athletes/4556590/2983174/1/large.jpg"}]}