{"id":6401771,"resource_state":3,"name":"La Raph'- part nine","activity_type":"NordicSki","distance":2132.9,"average_grade":-0.7,"maximum_grade":8.6,"elevation_high":1735.0,"elevation_low":1696.1,"start_latlng":[45.76253,6.513661],"end_latlng":[45.761992,6.515862],"start_latitude":45.76253,"start_longitude":6.513661,"end_latitude":45.761992,"end_longitude":6.515862,"climb_category":0,"city":"Cohennoz","state":"RA","country":"France","private":false,"hazardous":false,"starred":false,"created_at":"2014-01-10T20:32:42Z","updated_at":"2017-12-21T09:05:29Z","total_elevation_gain":37.7,"map":{"id":"s6401771","polyline":"y~hvGkewf@f@Yz@s@j@KVIt@QNIVSRYNYNk@P{@DIR[TK^e@`@]lAi@^WFA|@Tx@d@b@ErAu@\\_@Zi@j@e@tAyAz@gAvAwBRSXm@^e@Zq@ZeAX]Tg@h@aBRaAl@aBb@}@JYCm@HkAEYWg@SKKAK@wA|@ON]d@o@fB]rAu@jEq@pCm@z@g@b@kBT_A^uBnAw@r@o@VcBT_@Js@Js@Hu@@QBk@b@e@l@gAbBKTM^Q\\","resource_state":3},"effort_count":1288,"athlete_count":456,"star_count":0,"athlete_segment_stats":{"pr_elapsed_time":538,"pr_date":"2016-02-11","effort_count":3}}