{"effort_count":62,"entry_count":62,"neighborhood_count":1,"kom_type":"kom","entries":[{"athlete_name":"wilfrid coulot","athlete_id":2462629,"athlete_gender":"M","average_hr":null,"average_watts":null,"distance":175.0,"elapsed_time":42,"moving_time":42,"start_date":"2015-02-17T10:25:33Z","start_date_local":"2015-02-17T11:25:33Z","activity_id":256108561,"effort_id":5998668499,"rank":1,"neighborhood_index":0,"athlete_profile":"https://dgalywyr863hv.cloudfront.net/pictures/athletes/2462629/1288087/1/large.jpg"},{"athlete_name":"coulot charlélie","athlete_id":1930121,"athlete_gender":"M","average_hr":null,"average_watts":null,"distance":184.9,"elapsed_time":49,"moving_time":49,"start_date":"2016-03-19T09:43:29Z","start_date_local":"2016-03-19T10:43:29Z","activity_id":520983318,"effort_id":12522528754,"rank":2,"neighborhood_index":0,"athlete_profile":"https://dgalywyr863hv.cloudfront.net/pictures/athletes/1930121/2445374/4/large.jpg"},{"athlete_name":"nicolas veuriot","athlete_id":120710,"athlete_gender":"M","average_hr":131.5,"average_watts":null,"distance":181.4,"elapsed_time":51,"moving_time":51,"start_date":"2012-02-26T09:11:58Z","start_date_local":"2012-02-26T10:11:58Z","activity_id":4632509,"effort_id":2411624019,"rank":3,"neighborhood_index":0,"athlete_profile":"https://dgalywyr863hv.cloudfront.net/pictures/athletes/120710/1899823/1/large.jpg"},{"athlete_name":"Jean-François LECOULTRE","athlete_id":9024584,"athlete_gender":"M","average_hr":167.3,"average_watts":null,"distance":181.8,"elapsed_time":52,"moving_time":52,"start_date":"2015-01-25T10:08:51Z","start_date_local":"2015-01-25T11:08:51Z","activity_id":298247902,"effort_id":10045761363,"rank":4,"neighborhood_index":0,"athlete_profile":"https://dgalywyr863hv.cloudfront.net/pictures/athletes/9024584/5255959/1/large.jpg"},{"athlete_name":"benoit girardo","athlete_id":6315911,"athlete_gender":"M","average_hr":null,"average_watts":null,"distance":123.4,"elapsed_time":53,"moving_time":53,"start_date":"2015-03-14T11:00:22Z","start_date_local":"2015-03-14T12:00:22Z","activity_id":269733771,"effort_id":6406196408,"rank":5,"neighborhood_index":0,"athlete_profile":"avatar/athlete/large.png"},{"athlete_name":"LABBE Pierre","athlete_id":3393156,"athlete_gender":"M","average_hr":null,"average_watts":null,"distance":184.6,"elapsed_time":54,"moving_time":54,"start_date":"2013-12-31T08:44:49Z","start_date_local":"2013-12-31T09:44:49Z","activity_id":103172171,"effort_id":2411624003,"rank":6,"neighborhood_index":0,"athlete_profile":"https://dgalywyr863hv.cloudfront.net/pictures/athletes/3393156/2843148/1/large.jpg"},{"athlete_name":"cyril michaud-fidey","athlete_id":2151481,"athlete_gender":"M","average_hr":null,"average_watts":null,"distance":188.4,"elapsed_time":55,"moving_time":55,"start_date":"2014-03-01T06:06:49Z","start_date_local":"2014-03-01T07:06:49Z","activity_id":117435085,"effort_id":2712485164,"rank":7,"neighborhood_index":0,"athlete_profile":"https://dgalywyr863hv.cloudfront.net/pictures/athletes/2151481/754155/2/large.jpg"},{"athlete_name":"Kelly Genre-Grandpierre","athlete_id":9012190,"athlete_gender":"F","average_hr":null,"average_watts":null,"distance":180.8,"elapsed_time":55,"moving_time":55,"start_date":"2015-02-15T10:23:24Z","start_date_local":"2015-02-15T11:23:24Z","activity_id":297368116,"effort_id":6994106285,"rank":7,"neighborhood_index":0,"athlete_profile":"https://dgalywyr863hv.cloudfront.net/pictures/athletes/9012190/2727779/2/large.jpg"},{"athlete_name":"marc lobry","athlete_id":7118710,"athlete_gender":"M","average_hr":153.9,"average_watts":null,"distance":188.1,"elapsed_time":56,"moving_time":56,"start_date":"2015-02-25T19:53:25Z","start_date_local":"2015-02-25T20:53:25Z","activity_id":259831060,"effort_id":10044817069,"rank":9,"neighborhood_index":0,"athlete_profile":"https://dgalywyr863hv.cloudfront.net/pictures/athletes/7118710/2576050/1/large.jpg"}]}